npc_sessions/__init__.py
npc_sessions/py.typed
npc_sessions/sessions.py
npc_sessions/aind_data_schema/__init__.py
npc_sessions/aind_data_schema/acquisition.py
npc_sessions/aind_data_schema/data_description.py
npc_sessions/aind_data_schema/instrument.py
npc_sessions/trials/__init__.py
npc_sessions/trials/property_dict.py
npc_sessions/trials/TaskControl/DynamicRouting1.py
npc_sessions/trials/TaskControl/LuminanceTest.py
npc_sessions/trials/TaskControl/OptoTagging.py
npc_sessions/trials/TaskControl/RFMapping.py
npc_sessions/trials/TaskControl/__init__.py
npc_sessions/utils/__init__.py
npc_sessions/utils/electrodes.py
npc_sessions/utils/intervals.py
npc_sessions/utils/misc.py
npc_sessions/utils/units.py
npc_sessions/utils/videos.py
npc_sessions-0.0.274.dist-info/METADATA
npc_sessions-0.0.274.dist-info/WHEEL
npc_sessions-0.0.274.dist-info/entry_points.txt
npc_sessions-0.0.274.dist-info/top_level.txt
npc_sessions-0.0.274.dist-info/RECORD
