Metadata-Version: 2.4
Name: npc_sessions
Version: 0.0.274
Summary: NWB-conversion for behavior and epyhys sessions from the Mindscope Neuropixels team, in the cloud.
Author-email: Ben Hardcastle <ben.hardcastle@alleninstitute.org>, Arjun Sridhar <arjun.sridhar@alleninstitute.org>, Ethan McBride <ethan.mcbride@alleninstitute.org>, Corbett Bennett <corbettb@alleninstitute.org>, Sam Gale <samg@alleninstitute.org>, Christopher Mochizuki <chrism@alleninstitute.org>
License: MIT
Project-URL: Repository, https://github.com/AllenInstitute/npc_sessions
Project-URL: Issues, https://github.com/AllenInstitute/npc_sessions/issues
Classifier: Programming Language :: Python :: 3
Classifier: Programming Language :: Python :: 3.10
Classifier: Programming Language :: Python :: 3.11
Classifier: License :: OSI Approved :: MIT License
Classifier: Operating System :: Microsoft :: Windows
Classifier: Operating System :: POSIX :: Linux
Requires-Python: >=3.10
Requires-Dist: pandas>=2.0
Requires-Dist: pynwb<3.0,>=2.8.2
Requires-Dist: rich>=13.5.2
Requires-Dist: matplotlib>=3.7.2
Requires-Dist: scipy>=1.9.3
Requires-Dist: DynamicRoutingTask<0.1.106
Requires-Dist: numba>=0.57.1
Requires-Dist: python-dotenv>=1.0.0
Requires-Dist: ndx-events>=0.2.0
Requires-Dist: hdmf==3.14.6
Requires-Dist: ndx-pose>=0.1.1
Requires-Dist: tables>=3.9.2
Requires-Dist: pydantic<=2.7.4
Requires-Dist: npc-lims>=0.1.186
Requires-Dist: npc-sync>=0.1.25
Requires-Dist: npc-ephys>=0.1.35
Requires-Dist: npc-stim>=0.1.15
Requires-Dist: npc-samstim>=0.1.13
Requires-Dist: npc-session>=0.1.40
Requires-Dist: npc-mvr>=0.1.15
Requires-Dist: npc-io>=0.1.32
Requires-Dist: aind-session>=0.3.15
Requires-Dist: polars[pyarrow]>=1.24.0
Requires-Dist: numcodecs<=0.16
